py115/__init__.py
py115/cloud.py
py115/services.py
py115/types.py
py115/_internal/__init__.py
py115/_internal/oss.py
py115/_internal/utils.py
py115/_internal/api/__init__.py
py115/_internal/api/app.py
py115/_internal/api/dir.py
py115/_internal/api/file.py
py115/_internal/api/m115.py
py115/_internal/api/offline.py
py115/_internal/api/qrcode.py
py115/_internal/api/space.py
py115/_internal/api/upload.py
py115/_internal/api/user.py
py115/_internal/api/video.py
py115/_internal/crypto/__init__.py
py115/_internal/crypto/_rsa.py
py115/_internal/crypto/_xor.py
py115/_internal/crypto/ec115.py
py115/_internal/crypto/m115.py
py115/_internal/protocol/__init__.py
py115/_internal/protocol/api.py
py115/_internal/protocol/client.py
py115j-0.0.7.dist-info/LICENSE
py115j-0.0.7.dist-info/METADATA
py115j-0.0.7.dist-info/WHEEL
py115j-0.0.7.dist-info/top_level.txt
py115j-0.0.7.dist-info/RECORD
