Metadata-Version: 2.1
Name: py115j
Version: 0.0.7
Summary: Python SDK for 115 cloud storage service.
Author-email: deadblue <public@dead.blue>
License: MIT License
Project-URL: Homepage, https://github.com/jxxghp/py115
Project-URL: Documentation, https://py115.readthedocs.io/en/latest/
Keywords: 115,cloud-storage,sdk
Classifier: Development Status :: 3 - Alpha
Classifier: License :: OSI Approved :: MIT License
Classifier: Operating System :: OS Independent
Classifier: Programming Language :: Python :: 3 :: Only
Classifier: Programming Language :: Python :: 3.9
Classifier: Programming Language :: Python :: 3.10
Classifier: Programming Language :: Python :: 3.11
Classifier: Topic :: Software Development :: Libraries
Requires-Python: >=3.9
License-File: LICENSE
Requires-Dist: httpx (~=0.27.0)
Requires-Dist: lz4
Requires-Dist: pycryptodome (>=3.17.0)
Requires-Dist: pytz
Requires-Dist: requests
